<svg:svg xmlns:xlink='http://www.w3.org/1999/xlink' xmlns:svg='http://www.w3.org/2000/svg'>
  <svg:defs>
    <svg:style type="text/css"> 
      @import url("/public/examples/risk-first/risk-first.css"); 
    </svg:style>
  </svg:defs>
  <diagram xmlns="http://www.kite9.org/schema/adl" id="The Diagram" style="kite9-layout: down; kite9-padding: 0;">

    <table style="kite9-grid-size: 2 10; kite9-margin: 0; kite9-padding: 0">
      
      <cell style=" kite9-layout: down; ">
      </cell> 

    
      <cell style="kite9-occupies: 1 1 6 7; kite9-layout: right; ">
        <container layout="right" style="kite9-sizing: maximize; ">
          
          <label>
            <text>Scarcity</text>
            <symbols />
          </label>
        </container>

      </cell>

    </table>
  </diagram>

</svg:svg>